{
	"$schema": "http://schema.management.azure.com/schemas/2015-01-01/deploymentTemplate.json#",
	"contentVersion": "1.0.0.0",
	"parameters": {
		"factoryName": {
			"type": "string",
			"metadata": "Data Factory name",
			"defaultValue": "ADFFirstMohit"
		}
	},
	"variables": {
		"factoryId": "[concat('Microsoft.DataFactory/factories/', parameters('factoryName'))]"
	},
	"resources": [
		{
			"name": "[concat(parameters('factoryName'), '/copyallot')]",
			"type": "Microsoft.DataFactory/factories/datasets",
			"apiVersion": "2018-06-01",
			"properties": {
				"linkedServiceName": {
					"referenceName": "Linkedservice_SqlServer",
					"type": "LinkedServiceReference"
				},
				"annotations": [],
				"type": "SqlServerTable",
				"schema": [],
				"typeProperties": {
					"schema": "dbo",
					"table": "Allotments"
				}
			},
			"dependsOn": []
		},
		{
			"name": "[concat(parameters('factoryName'), '/lookupforFetchsp')]",
			"type": "Microsoft.DataFactory/factories/datasets",
			"apiVersion": "2018-06-01",
			"properties": {
				"linkedServiceName": {
					"referenceName": "Linkedservice_SqlServer",
					"type": "LinkedServiceReference"
				},
				"folder": {
					"name": "CTtask3datasets"
				},
				"annotations": [],
				"type": "SqlServerTable",
				"schema": [],
				"typeProperties": {
					"schema": ""
				}
			},
			"dependsOn": []
		},
		{
			"name": "[concat(parameters('factoryName'), '/t3SSMSoutputinstg')]",
			"type": "Microsoft.DataFactory/factories/datasets",
			"apiVersion": "2018-06-01",
			"properties": {
				"linkedServiceName": {
					"referenceName": "Linkedservice_SqlServer",
					"type": "LinkedServiceReference"
				},
				"parameters": {
					"fileName": {
						"type": "string"
					}
				},
				"folder": {
					"name": "CTtask3datasets"
				},
				"annotations": [],
				"type": "SqlServerTable",
				"schema": [],
				"typeProperties": {
					"schema": "stg",
					"table": {
						"value": "@dataset().fileName",
						"type": "Expression"
					}
				}
			},
			"dependsOn": []
		},
		{
			"name": "[concat(parameters('factoryName'), '/FinalTaskfetchspLookup')]",
			"type": "Microsoft.DataFactory/factories/datasets",
			"apiVersion": "2018-06-01",
			"properties": {
				"linkedServiceName": {
					"referenceName": "Linkedservice_SqlServer",
					"type": "LinkedServiceReference"
				},
				"folder": {
					"name": "CTFinalTAsk"
				},
				"annotations": [],
				"type": "SqlServerTable",
				"schema": [],
				"typeProperties": {}
			},
			"dependsOn": []
		},
		{
			"name": "[concat(parameters('factoryName'), '/Studentpreferencepipe')]",
			"type": "Microsoft.DataFactory/factories/pipelines",
			"apiVersion": "2018-06-01",
			"properties": {
				"activities": [
					{
						"name": "Lookup1",
						"type": "Lookup",
						"dependsOn": [],
						"policy": {
							"timeout": "7.00:00:00",
							"retry": 0,
							"retryIntervalInSeconds": 30,
							"secureOutput": false,
							"secureInput": false
						},
						"userProperties": [],
						"typeProperties": {
							"source": {
								"type": "DelimitedTextSource",
								"storeSettings": {
									"type": "AzureBlobStorageReadSettings",
									"recursive": true,
									"enablePartitionDiscovery": false
								},
								"formatSettings": {
									"type": "DelimitedTextReadSettings"
								}
							},
							"dataset": {
								"referenceName": "Studentlookupinput",
								"type": "DatasetReference",
								"parameters": {}
							},
							"firstRowOnly": false
						}
					},
					{
						"name": "ForEach1",
						"type": "ForEach",
						"dependsOn": [
							{
								"activity": "Lookup1",
								"dependencyConditions": [
									"Succeeded"
								]
							}
						],
						"userProperties": [],
						"typeProperties": {
							"items": {
								"value": "@activity('Lookup1').output.value",
								"type": "Expression"
							},
							"isSequential": true,
							"activities": [
								{
									"name": "Stored procedure1",
									"type": "SqlServerStoredProcedure",
									"dependsOn": [],
									"policy": {
										"timeout": "7.00:00:00",
										"retry": 0,
										"retryIntervalInSeconds": 30,
										"secureOutput": false,
										"secureInput": false
									},
									"userProperties": [],
									"typeProperties": {
										"storedProcedureName": "[[dbo].[selectpreference]",
										"storedProcedureParameters": {
											"studentid_value": {
												"value": {
													"value": "@item().StudentId",
													"type": "Expression"
												},
												"type": "Int32"
											}
										}
									},
									"linkedServiceName": {
										"referenceName": "Linkedservice_SqlServer",
										"type": "LinkedServiceReference"
									}
								}
							]
						}
					},
					{
						"name": "Copy data1",
						"type": "Copy",
						"dependsOn": [
							{
								"activity": "ForEach1",
								"dependencyConditions": [
									"Succeeded"
								]
							}
						],
						"policy": {
							"timeout": "7.00:00:00",
							"retry": 0,
							"retryIntervalInSeconds": 30,
							"secureOutput": false,
							"secureInput": false
						},
						"userProperties": [],
						"typeProperties": {
							"source": {
								"type": "SqlServerSource",
								"queryTimeout": "02:00:00",
								"partitionOption": "None"
							},
							"sink": {
								"type": "DelimitedTextSink",
								"storeSettings": {
									"type": "AzureBlobStorageWriteSettings"
								},
								"formatSettings": {
									"type": "DelimitedTextWriteSettings",
									"quoteAllText": true,
									"fileExtension": ".txt"
								}
							},
							"enableStaging": false,
							"translator": {
								"type": "TabularTranslator",
								"typeConversion": true,
								"typeConversionSettings": {
									"allowDataTruncation": true,
									"treatBooleanAsNumber": false
								}
							}
						},
						"inputs": [
							{
								"referenceName": "copyallot",
								"type": "DatasetReference",
								"parameters": {}
							}
						],
						"outputs": [
							{
								"referenceName": "blobcopy",
								"type": "DatasetReference",
								"parameters": {}
							}
						]
					}
				],
				"policy": {
					"elapsedTimeMetric": {},
					"cancelAfter": {}
				},
				"annotations": [],
				"lastPublishTime": "2022-08-05T17:45:58Z"
			},
			"dependsOn": [
				"[concat(variables('factoryId'), '/datasets/copyallot')]"
			]
		},
		{
			"name": "[concat(parameters('factoryName'), '/csvfilesloading')]",
			"type": "Microsoft.DataFactory/factories/pipelines",
			"apiVersion": "2018-06-01",
			"properties": {
				"activities": [
					{
						"name": "Lookup1",
						"type": "Lookup",
						"dependsOn": [],
						"policy": {
							"timeout": "7.00:00:00",
							"retry": 0,
							"retryIntervalInSeconds": 30,
							"secureOutput": false,
							"secureInput": false
						},
						"userProperties": [],
						"typeProperties": {
							"source": {
								"type": "DelimitedTextSource",
								"storeSettings": {
									"type": "AzureBlobStorageReadSettings",
									"recursive": true,
									"enablePartitionDiscovery": false
								},
								"formatSettings": {
									"type": "DelimitedTextReadSettings"
								}
							},
							"dataset": {
								"referenceName": "allcsvnamesfiles",
								"type": "DatasetReference",
								"parameters": {}
							},
							"firstRowOnly": false
						}
					},
					{
						"name": "ForEach1",
						"type": "ForEach",
						"dependsOn": [
							{
								"activity": "Lookup1",
								"dependencyConditions": [
									"Succeeded"
								]
							}
						],
						"userProperties": [],
						"typeProperties": {
							"items": {
								"value": "@activity('Lookup1').output.value",
								"type": "Expression"
							},
							"isSequential": true,
							"activities": [
								{
									"name": "Copy data1",
									"type": "Copy",
									"dependsOn": [],
									"policy": {
										"timeout": "7.00:00:00",
										"retry": 0,
										"retryIntervalInSeconds": 30,
										"secureOutput": false,
										"secureInput": false
									},
									"userProperties": [],
									"typeProperties": {
										"source": {
											"type": "DelimitedTextSource",
											"storeSettings": {
												"type": "AzureBlobStorageReadSettings",
												"recursive": true,
												"enablePartitionDiscovery": false
											},
											"formatSettings": {
												"type": "DelimitedTextReadSettings"
											}
										},
										"sink": {
											"type": "SqlServerSink",
											"writeBehavior": "insert",
											"sqlWriterUseTableLock": false,
											"tableOption": "autoCreate"
										},
										"enableStaging": false,
										"translator": {
											"type": "TabularTranslator",
											"typeConversion": true,
											"typeConversionSettings": {
												"allowDataTruncation": true,
												"treatBooleanAsNumber": false
											}
										}
									},
									"inputs": [
										{
											"referenceName": "copydata",
											"type": "DatasetReference",
											"parameters": {
												"File_Name": {
													"value": "@item().File_Name",
													"type": "Expression"
												}
											}
										}
									],
									"outputs": [
										{
											"referenceName": "SSMSoutput",
											"type": "DatasetReference",
											"parameters": {
												"File_Name": {
													"value": "@item().File_Name",
													"type": "Expression"
												}
											}
										}
									]
								}
							]
						}
					}
				],
				"policy": {
					"elapsedTimeMetric": {},
					"cancelAfter": {}
				},
				"annotations": [],
				"lastPublishTime": "2022-08-04T13:01:19Z"
			},
			"dependsOn": []
		},
		{
			"name": "[concat(parameters('factoryName'), '/t3triggerpipeline')]",
			"type": "Microsoft.DataFactory/factories/pipelines",
			"apiVersion": "2018-06-01",
			"properties": {
				"activities": [
					{
						"name": "lookupatSP",
						"type": "Lookup",
						"dependsOn": [],
						"policy": {
							"timeout": "7.00:00:00",
							"retry": 0,
							"retryIntervalInSeconds": 30,
							"secureOutput": false,
							"secureInput": false
						},
						"userProperties": [],
						"typeProperties": {
							"source": {
								"type": "SqlServerSource",
								"sqlReaderQuery": "SELECT \n  ROUTINE_SCHEMA,\n  ROUTINE_NAME\nFROM INFORMATION_SCHEMA.ROUTINES\nWHERE ROUTINE_TYPE = 'PROCEDURE';",
								"queryTimeout": "02:00:00",
								"partitionOption": "None"
							},
							"dataset": {
								"referenceName": "lookupforFetchsp",
								"type": "DatasetReference",
								"parameters": {}
							},
							"firstRowOnly": false
						}
					},
					{
						"name": "iterateSP",
						"type": "ForEach",
						"dependsOn": [
							{
								"activity": "lookupatSP",
								"dependencyConditions": [
									"Succeeded"
								]
							}
						],
						"userProperties": [],
						"typeProperties": {
							"items": {
								"value": "@activity('lookupatSP').output.value",
								"type": "Expression"
							},
							"isSequential": true,
							"activities": [
								{
									"name": "Stored procedure1",
									"type": "SqlServerStoredProcedure",
									"dependsOn": [],
									"policy": {
										"timeout": "7.00:00:00",
										"retry": 0,
										"retryIntervalInSeconds": 30,
										"secureOutput": false,
										"secureInput": false
									},
									"userProperties": [],
									"typeProperties": {
										"storedProcedureName": {
											"value": "@item().ROUTINE_NAME",
											"type": "Expression"
										}
									},
									"linkedServiceName": {
										"referenceName": "Linkedservice_SqlServer",
										"type": "LinkedServiceReference"
									}
								}
							]
						}
					}
				],
				"policy": {
					"elapsedTimeMetric": {},
					"cancelAfter": {}
				},
				"annotations": [],
				"lastPublishTime": "2022-08-20T11:17:27Z"
			},
			"dependsOn": [
				"[concat(variables('factoryId'), '/datasets/lookupforFetchsp')]"
			]
		},
		{
			"name": "[concat(parameters('factoryName'), '/CTfinaltaskOutput')]",
			"type": "Microsoft.DataFactory/factories/pipelines",
			"apiVersion": "2018-06-01",
			"properties": {
				"activities": [
					{
						"name": "Lookupatsp",
						"type": "Lookup",
						"dependsOn": [],
						"policy": {
							"timeout": "0.12:00:00",
							"retry": 0,
							"retryIntervalInSeconds": 30,
							"secureOutput": false,
							"secureInput": false
						},
						"userProperties": [],
						"typeProperties": {
							"source": {
								"type": "SqlServerSource",
								"sqlReaderQuery": "SELECT TOP 3 [NAME] from sysobjects where type ='P' and category =0",
								"queryTimeout": "02:00:00",
								"partitionOption": "None"
							},
							"dataset": {
								"referenceName": "FinalTaskfetchspLookup",
								"type": "DatasetReference",
								"parameters": {}
							},
							"firstRowOnly": false
						}
					},
					{
						"name": "ForEach1",
						"type": "ForEach",
						"dependsOn": [
							{
								"activity": "Lookupatsp",
								"dependencyConditions": [
									"Succeeded"
								]
							}
						],
						"userProperties": [],
						"typeProperties": {
							"items": {
								"value": "@activity('Lookupatsp').output.value",
								"type": "Expression"
							},
							"isSequential": true,
							"activities": [
								{
									"name": "Stored procedure1",
									"type": "SqlServerStoredProcedure",
									"dependsOn": [],
									"policy": {
										"timeout": "0.12:00:00",
										"retry": 0,
										"retryIntervalInSeconds": 30,
										"secureOutput": false,
										"secureInput": false
									},
									"userProperties": [],
									"typeProperties": {
										"storedProcedureName": {
											"value": "@item().NAME",
											"type": "Expression"
										}
									},
									"linkedServiceName": {
										"referenceName": "Linkedservice_SqlServer",
										"type": "LinkedServiceReference"
									}
								}
							]
						}
					}
				],
				"policy": {
					"elapsedTimeMetric": {},
					"cancelAfter": {}
				},
				"annotations": []
			},
			"dependsOn": [
				"[concat(variables('factoryId'), '/datasets/FinalTaskfetchspLookup')]"
			]
		},
		{
			"name": "[concat(parameters('factoryName'), '/CTFilnalTaskinSSMS')]",
			"type": "Microsoft.DataFactory/factories/pipelines",
			"apiVersion": "2018-06-01",
			"properties": {
				"activities": [
					{
						"name": "FinaltaskCSVlookup",
						"type": "Lookup",
						"dependsOn": [],
						"policy": {
							"timeout": "7.00:00:00",
							"retry": 0,
							"retryIntervalInSeconds": 30,
							"secureOutput": false,
							"secureInput": false
						},
						"userProperties": [],
						"typeProperties": {
							"source": {
								"type": "DelimitedTextSource",
								"storeSettings": {
									"type": "AzureBlobStorageReadSettings",
									"recursive": true,
									"enablePartitionDiscovery": false
								},
								"formatSettings": {
									"type": "DelimitedTextReadSettings"
								}
							},
							"dataset": {
								"referenceName": "CTFInalTaskCsvLookupIP",
								"type": "DatasetReference",
								"parameters": {}
							},
							"firstRowOnly": false
						}
					},
					{
						"name": "ForEachFinalTaskfiles",
						"type": "ForEach",
						"dependsOn": [
							{
								"activity": "FinaltaskCSVlookup",
								"dependencyConditions": [
									"Succeeded"
								]
							}
						],
						"userProperties": [],
						"typeProperties": {
							"items": {
								"value": "@activity('FinaltaskCSVlookup').output.value",
								"type": "Expression"
							},
							"isSequential": true,
							"activities": [
								{
									"name": "CopyCsvtoStginSSMS",
									"type": "Copy",
									"dependsOn": [],
									"policy": {
										"timeout": "7.00:00:00",
										"retry": 0,
										"retryIntervalInSeconds": 30,
										"secureOutput": false,
										"secureInput": false
									},
									"userProperties": [],
									"typeProperties": {
										"source": {
											"type": "DelimitedTextSource",
											"storeSettings": {
												"type": "AzureBlobStorageReadSettings",
												"recursive": true,
												"enablePartitionDiscovery": false
											},
											"formatSettings": {
												"type": "DelimitedTextReadSettings"
											}
										},
										"sink": {
											"type": "SqlServerSink",
											"writeBehavior": "insert",
											"sqlWriterUseTableLock": false,
											"tableOption": "autoCreate"
										},
										"enableStaging": false,
										"translator": {
											"type": "TabularTranslator",
											"typeConversion": true,
											"typeConversionSettings": {
												"allowDataTruncation": true,
												"treatBooleanAsNumber": false
											}
										}
									},
									"inputs": [
										{
											"referenceName": "FinalTaskCSVcopy",
											"type": "DatasetReference",
											"parameters": {
												"filename": {
													"value": "@item().filename",
													"type": "Expression"
												}
											}
										}
									],
									"outputs": [
										{
											"referenceName": "FinaltaskCSVinStg",
											"type": "DatasetReference",
											"parameters": {
												"filename": {
													"value": "@replace(item().filename,'.csv','')",
													"type": "Expression"
												}
											}
										}
									]
								}
							]
						}
					},
					{
						"name": "Execute Pipeline1",
						"type": "ExecutePipeline",
						"dependsOn": [
							{
								"activity": "ForEachFinalTaskfiles",
								"dependencyConditions": [
									"Succeeded"
								]
							}
						],
						"userProperties": [],
						"typeProperties": {
							"pipeline": {
								"referenceName": "CTfinaltaskOutput",
								"type": "PipelineReference"
							},
							"waitOnCompletion": true,
							"parameters": {}
						}
					}
				],
				"policy": {
					"elapsedTimeMetric": {},
					"cancelAfter": {}
				},
				"annotations": []
			},
			"dependsOn": [
				"[concat(variables('factoryId'), '/pipelines/CTfinaltaskOutput')]"
			]
		},
		{
			"name": "[concat(parameters('factoryName'), '/CTtask3csvtoSSMSinStg')]",
			"type": "Microsoft.DataFactory/factories/pipelines",
			"apiVersion": "2018-06-01",
			"properties": {
				"activities": [
					{
						"name": "Lookup1",
						"type": "Lookup",
						"dependsOn": [],
						"policy": {
							"timeout": "7.00:00:00",
							"retry": 0,
							"retryIntervalInSeconds": 30,
							"secureOutput": false,
							"secureInput": false
						},
						"userProperties": [],
						"typeProperties": {
							"source": {
								"type": "DelimitedTextSource",
								"storeSettings": {
									"type": "AzureBlobStorageReadSettings",
									"recursive": true,
									"enablePartitionDiscovery": false
								},
								"formatSettings": {
									"type": "DelimitedTextReadSettings"
								}
							},
							"dataset": {
								"referenceName": "task3Lookup1IP",
								"type": "DatasetReference",
								"parameters": {}
							},
							"firstRowOnly": false
						}
					},
					{
						"name": "ForEach1",
						"type": "ForEach",
						"dependsOn": [
							{
								"activity": "Lookup1",
								"dependencyConditions": [
									"Succeeded"
								]
							}
						],
						"userProperties": [],
						"typeProperties": {
							"items": {
								"value": "@activity('Lookup1').output.value",
								"type": "Expression"
							},
							"isSequential": true,
							"activities": [
								{
									"name": "Copy data1",
									"type": "Copy",
									"dependsOn": [],
									"policy": {
										"timeout": "7.00:00:00",
										"retry": 0,
										"retryIntervalInSeconds": 30,
										"secureOutput": false,
										"secureInput": false
									},
									"userProperties": [],
									"typeProperties": {
										"source": {
											"type": "DelimitedTextSource",
											"storeSettings": {
												"type": "AzureBlobStorageReadSettings",
												"recursive": true,
												"enablePartitionDiscovery": false
											},
											"formatSettings": {
												"type": "DelimitedTextReadSettings"
											}
										},
										"sink": {
											"type": "SqlServerSink",
											"writeBehavior": "insert",
											"sqlWriterUseTableLock": false,
											"tableOption": "autoCreate"
										},
										"enableStaging": false,
										"translator": {
											"type": "TabularTranslator",
											"typeConversion": true,
											"typeConversionSettings": {
												"allowDataTruncation": true,
												"treatBooleanAsNumber": false
											}
										}
									},
									"inputs": [
										{
											"referenceName": "t3copyCSVtoSSMSIP",
											"type": "DatasetReference",
											"parameters": {
												"fileName": {
													"value": "@item().fileName",
													"type": "Expression"
												}
											}
										}
									],
									"outputs": [
										{
											"referenceName": "t3SSMSoutputinstg",
											"type": "DatasetReference",
											"parameters": {
												"fileName": {
													"value": "@replace(item().fileName,'.csv','')",
													"type": "Expression"
												}
											}
										}
									]
								}
							]
						}
					},
					{
						"name": "Execute Pipeline1",
						"type": "ExecutePipeline",
						"dependsOn": [
							{
								"activity": "ForEach1",
								"dependencyConditions": [
									"Succeeded"
								]
							}
						],
						"userProperties": [],
						"typeProperties": {
							"pipeline": {
								"referenceName": "t3triggerpipeline",
								"type": "PipelineReference"
							},
							"waitOnCompletion": true,
							"parameters": {}
						}
					}
				],
				"policy": {
					"elapsedTimeMetric": {},
					"cancelAfter": {}
				},
				"annotations": [],
				"lastPublishTime": "2022-08-20T11:33:49Z"
			},
			"dependsOn": [
				"[concat(variables('factoryId'), '/pipelines/t3triggerpipeline')]",
				"[concat(variables('factoryId'), '/datasets/t3SSMSoutputinstg')]"
			]
		}
	]
}