{
	"name": "CTFInalTaskCsvLookupIP",
	"properties": {
		"linkedServiceName": {
			"referenceName": "linkedservice_storagefirst",
			"type": "LinkedServiceReference"
		},
		"folder": {
			"name": "CTFinalTAsk"
		},
		"annotations": [],
		"type": "DelimitedText",
		"typeProperties": {
			"location": {
				"type": "AzureBlobStorageLocation",
				"fileName": "allfilesofFinalTask.csv",
				"container": "containercsv"
			},
			"columnDelimiter": ",",
			"escapeChar": "\\",
			"firstRowAsHeader": true,
			"quoteChar": "\""
		},
		"schema": []
	}
}